ibeis/__init__.py
ibeis/__main__.py
ibeis/_devcmds_ibeis.py
ibeis/_devscript.py
ibeis/_ibeis_object.py
ibeis/annotmatch_funcs.py
ibeis/annots.py
ibeis/constants.py
ibeis/core_annots.py
ibeis/core_images.py
ibeis/core_parts.py
ibeis/demodata.py
ibeis/dev.py
ibeis/filter_configs.py
ibeis/images.py
ibeis/main_module.py
ibeis/params.py
ibeis/tag_funcs.py
ibeis/algo/Config.py
ibeis/algo/__init__.py
ibeis/algo/detect/__init__.py
ibeis/algo/detect/azure.py
ibeis/algo/detect/darknet.py
ibeis/algo/detect/fasterrcnn.py
ibeis/algo/detect/grabmodels.py
ibeis/algo/detect/lightnet.py
ibeis/algo/detect/randomforest.py
ibeis/algo/detect/rf.py
ibeis/algo/detect/selectivesearch.py
ibeis/algo/detect/ssd.py
ibeis/algo/detect/svm.py
ibeis/algo/detect/yolo.py
ibeis/algo/detect/nms/__init__.py
ibeis/algo/detect/nms/py_cpu_nms.py
ibeis/algo/graph/__init__.py
ibeis/algo/graph/__main__.py
ibeis/algo/graph/core.py
ibeis/algo/graph/demo.py
ibeis/algo/graph/mixin_dynamic.py
ibeis/algo/graph/mixin_groundtruth.py
ibeis/algo/graph/mixin_helpers.py
ibeis/algo/graph/mixin_ibeis.py
ibeis/algo/graph/mixin_loops.py
ibeis/algo/graph/mixin_matching.py
ibeis/algo/graph/mixin_priority.py
ibeis/algo/graph/mixin_simulation.py
ibeis/algo/graph/mixin_viz.py
ibeis/algo/graph/nx_dynamic_graph.py
ibeis/algo/graph/nx_edge_augmentation.py
ibeis/algo/graph/nx_edge_kcomponents.py
ibeis/algo/graph/nx_utils.py
ibeis/algo/graph/refresh.py
ibeis/algo/graph/state.py
ibeis/algo/graph/tests/__init__.py
ibeis/algo/graph/tests/dyn_cases.py
ibeis/algo/graph/tests/test_graph_iden.py
ibeis/algo/graph/tests/test_neg_metagraph.py
ibeis/algo/hots/__init__.py
ibeis/algo/hots/_pipeline_helpers.py
ibeis/algo/hots/chip_match.py
ibeis/algo/hots/exceptions.py
ibeis/algo/hots/hstypes.py
ibeis/algo/hots/match_chips4.py
ibeis/algo/hots/name_scoring.py
ibeis/algo/hots/neighbor_index.py
ibeis/algo/hots/neighbor_index_cache.py
ibeis/algo/hots/nn_weights.py
ibeis/algo/hots/old_chip_match.py
ibeis/algo/hots/pipeline.py
ibeis-2.4.0.dist-info/licenses/LICENSE
ibeis-2.4.0.dist-info/METADATA
ibeis-2.4.0.dist-info/WHEEL
ibeis-2.4.0.dist-info/entry_points.txt
ibeis-2.4.0.dist-info/top_level.txt
ibeis-2.4.0.dist-info/RECORD
