Metadata-Version: 2.4
Name: ibeis
Version: 2.4.0
Summary: IBEIS - Image Based Ecological Information System
Home-page: https://github.com/Erotemic/ibeis
Author: Jon Crall, Jason Parham
Author-email: erotemic@gmail.com
License: Apache 2
Classifier: Development Status :: 5 - Production/Stable
Classifier: Intended Audience :: Developers
Classifier: Topic :: Software Development :: Libraries :: Python Modules
Classifier: Topic :: Utilities
Classifier: License :: OSI Approved :: Apache Software License
Classifier: Programming Language :: Python :: 3.8
Classifier: Programming Language :: Python :: 3.9
Classifier: Programming Language :: Python :: 3.10
Classifier: Programming Language :: Python :: 3.11
Requires-Python: >=3.8
License-File: LICENSE
Requires-Dist: utool>=2.2.0
Requires-Dist: vtool_ibeis>=2.3.0
Requires-Dist: dtool_ibeis>=1.1.2
Requires-Dist: plottool_ibeis>=2.3.0
Requires-Dist: guitool_ibeis>=2.2.0
Requires-Dist: futures_actors>=0.0.5
Requires-Dist: pyflann_ibeis>=2.4.1
Requires-Dist: vtool_ibeis_ext>=0.1.2
Requires-Dist: pyhesaff>=2.1.3
Requires-Dist: flask>=2.1.3
Requires-Dist: Werkzeug>=2.2.2
Requires-Dist: pygments>=2.11.2
Requires-Dist: packaging>=21.3; python_version >= "3.6"
Requires-Dist: boto>=2.49.0
Requires-Dist: colorama>=0.3.2
Requires-Dist: IPython>=7.16.2
Requires-Dist: parse>=1.19.0
Requires-Dist: pyasn1>=0.4.8
Requires-Dist: pyzmq>=26.0.0; python_version < "4.0" and python_version >= "3.13"
Requires-Dist: pyzmq>=26.0.0; python_version < "3.13" and python_version >= "3.12"
Requires-Dist: pyzmq>=25.0.0; python_version < "3.12"
Requires-Dist: setuptools>=34.1.0
Requires-Dist: simplejson>=3.6.5
Requires-Dist: six>=1.16.0
Requires-Dist: lockfile>=0.10.2
Requires-Dist: statsmodels>=0.14.3; python_version < "4.0" and python_version >= "3.13"
Requires-Dist: statsmodels>=0.14.0; python_version < "3.13" and python_version >= "3.12"
Requires-Dist: statsmodels>=0.13.3; python_version < "3.12" and python_version >= "3.11"
Requires-Dist: statsmodels>=0.13.1; python_version < "3.11" and python_version >= "3.10"
Requires-Dist: statsmodels>=0.13.1; python_version < "3.10" and python_version >= "3.9"
Requires-Dist: ubelt>=1.3.4
Requires-Dist: pyqt5>=5.15.10; python_version < "4.0" and python_version >= "3.12"
Requires-Dist: pyqt5>=5.15.5; python_version < "3.12" and python_version >= "2.7"
Requires-Dist: pynmea2>=1.13.0; python_version < "4.0" and python_version >= "3.12"
Requires-Dist: pynmea2>=1.5.3; python_version < "3.12" and python_version >= "3.6"
Requires-Dist: tornado>=6.2
Requires-Dist: psutil>=6.1.0; python_version < "4.0" and python_version >= "3.13"
Requires-Dist: psutil>=5.9.6; python_version < "3.13" and python_version >= "3.12"
Requires-Dist: psutil>=5.9.4; python_version < "3.12" and python_version >= "3.11"
Requires-Dist: psutil>=5.9.0; python_version < "3.11" and python_version >= "3.10"
Requires-Dist: psutil>=5.9.0; python_version < "3.10" and python_version >= "3.9"
Requires-Dist: matplotlib>=3.9.2; python_version < "4.0" and python_version >= "3.13"
Requires-Dist: matplotlib>=3.8.4; python_version < "3.13" and python_version >= "3.12"
Requires-Dist: matplotlib>=3.5.0; python_version < "3.12" and python_version >= "3.11"
Requires-Dist: matplotlib>=3.3.3; python_version < "3.10" and python_version >= "3.9"
Requires-Dist: matplotlib>=1.5.3; python_version < "3.7" and python_version >= "3.6"
Requires-Dist: numpy>=2.1.0; python_version < "4.0" and python_version >= "3.13"
Requires-Dist: numpy>=1.26.0; python_version < "3.13" and python_version >= "3.12"
Requires-Dist: numpy>=1.24.0; python_version < "3.12" and python_version >= "3.11"
Requires-Dist: numpy>=1.21.6; python_version < "3.11" and python_version >= "3.10"
Requires-Dist: numpy>=1.19.3; python_version < "3.10" and python_version >= "3.9"
Requires-Dist: scikit-image>=0.25.1; python_version < "4.0" and python_version >= "3.13"
Requires-Dist: scikit-image>=0.22.0; python_version < "3.13" and python_version >= "3.12"
Requires-Dist: scikit-image>=0.20.0; python_version < "3.12" and python_version >= "3.11"
Requires-Dist: scikit-image>=0.19.0; python_version < "3.11" and python_version >= "3.10"
Requires-Dist: scikit-image>=0.18.0; python_version < "3.10" and python_version >= "3.9"
Requires-Dist: scikit-learn>=1.5.2; python_version < "4.0" and python_version >= "3.13"
Requires-Dist: scikit-learn>=1.3.1; python_version < "3.13" and python_version >= "3.12"
Requires-Dist: scikit-learn>=1.1.3; python_version < "3.12" and python_version >= "3.11"
Requires-Dist: scikit-learn>=1.1.0; python_version < "3.11" and python_version >= "3.10"
Requires-Dist: scikit-learn>=1.0.2; python_version < "3.10" and python_version >= "3.9"
Requires-Dist: scipy>=1.14.1; python_version < "4.0" and python_version >= "3.13"
Requires-Dist: scipy>=1.11.2; python_version < "3.13" and python_version >= "3.12"
Requires-Dist: scipy>=1.9.2; python_version < "3.12" and python_version >= "3.11"
Requires-Dist: scipy>=1.8.0; python_version < "3.11" and python_version >= "3.10"
Requires-Dist: scipy>=1.8.0; python_version < "3.10" and python_version >= "3.9"
Requires-Dist: shapely>=2.0.6; python_version < "4.0" and python_version >= "3.13"
Requires-Dist: shapely>=2.0.2; python_version < "3.13" and python_version >= "3.12"
Requires-Dist: shapely>=2.0.1; python_version < "3.12" and python_version >= "3.11"
Requires-Dist: shapely>=1.8.2; python_version < "3.11" and python_version >= "3.10"
Requires-Dist: shapely>=1.7.1; python_version < "3.10" and python_version >= "3.9"
Requires-Dist: networkx>=3.0.0; python_version < "4.0" and python_version >= "3.13"
Requires-Dist: networkx>=2.8; python_version < "3.13" and python_version >= "3.11"
Requires-Dist: networkx>=2.7; python_version < "3.11" and python_version >= "3.8"
Requires-Dist: pandas>=2.2.3; python_version < "4.0" and python_version >= "3.13"
Requires-Dist: pandas>=2.1.1; python_version < "3.13" and python_version >= "3.12"
Requires-Dist: pandas>=1.5.0; python_version < "3.12" and python_version >= "3.11"
Requires-Dist: pandas>=1.3.5; python_version < "3.11" and python_version >= "3.10"
Requires-Dist: pandas>=1.4.0; python_version < "3.10" and python_version >= "3.9"
Requires-Dist: Pillow>=11.3.0; python_version < "4.0" and python_version >= "3.13"
Requires-Dist: Pillow>=10.0.0; python_version < "3.13" and python_version >= "3.12"
Requires-Dist: Pillow>=9.4.0; python_version < "3.12" and python_version >= "3.11"
Requires-Dist: Pillow>=9.1.0; python_version < "3.11" and python_version >= "3.10"
Requires-Dist: Pillow>=8.3.2; python_version < "3.10" and python_version >= "3.9"
Requires-Dist: cachetools>=5.0.0; python_version < "4.0" and python_version >= "3.11"
Requires-Dist: cachetools>=5.0.0; python_version < "3.11" and python_version >= "3.10"
Requires-Dist: cachetools>=4.2.0; python_version < "3.10" and python_version >= "3.9"
Requires-Dist: pyparsing>=3.0.7
Requires-Dist: requests>=2.27.1
Requires-Dist: safer>=4.4.1
Provides-Extra: all
Requires-Dist: utool>=2.2.0; extra == "all"
Requires-Dist: vtool_ibeis>=2.3.0; extra == "all"
Requires-Dist: dtool_ibeis>=1.1.2; extra == "all"
Requires-Dist: plottool_ibeis>=2.3.0; extra == "all"
Requires-Dist: guitool_ibeis>=2.2.0; extra == "all"
Requires-Dist: futures_actors>=0.0.5; extra == "all"
Requires-Dist: pyflann_ibeis>=2.4.1; extra == "all"
Requires-Dist: vtool_ibeis_ext>=0.1.2; extra == "all"
Requires-Dist: pyhesaff>=2.1.3; extra == "all"
Requires-Dist: flask>=2.1.3; extra == "all"
Requires-Dist: Werkzeug>=2.2.2; extra == "all"
Requires-Dist: pygments>=2.11.2; extra == "all"
Requires-Dist: packaging>=21.3; python_version >= "3.6" and extra == "all"
Requires-Dist: boto>=2.49.0; extra == "all"
Requires-Dist: colorama>=0.3.2; extra == "all"
Requires-Dist: IPython>=7.16.2; extra == "all"
Requires-Dist: parse>=1.19.0; extra == "all"
Requires-Dist: pyasn1>=0.4.8; extra == "all"
Requires-Dist: pyzmq>=26.0.0; (python_version < "4.0" and python_version >= "3.13") and extra == "all"
Requires-Dist: pyzmq>=26.0.0; (python_version < "3.13" and python_version >= "3.12") and extra == "all"
Requires-Dist: pyzmq>=25.0.0; python_version < "3.12" and extra == "all"
Requires-Dist: setuptools>=34.1.0; extra == "all"
Requires-Dist: simplejson>=3.6.5; extra == "all"
Requires-Dist: six>=1.16.0; extra == "all"
Requires-Dist: lockfile>=0.10.2; extra == "all"
Requires-Dist: statsmodels>=0.14.3; (python_version < "4.0" and python_version >= "3.13") and extra == "all"
Requires-Dist: statsmodels>=0.14.0; (python_version < "3.13" and python_version >= "3.12") and extra == "all"
Requires-Dist: statsmodels>=0.13.3; (python_version < "3.12" and python_version >= "3.11") and extra == "all"
Requires-Dist: statsmodels>=0.13.1; (python_version < "3.11" and python_version >= "3.10") and extra == "all"
Requires-Dist: statsmodels>=0.13.1; (python_version < "3.10" and python_version >= "3.9") and extra == "all"
Requires-Dist: ubelt>=1.3.4; extra == "all"
Requires-Dist: pyqt5>=5.15.10; (python_version < "4.0" and python_version >= "3.12") and extra == "all"
Requires-Dist: pyqt5>=5.15.5; (python_version < "3.12" and python_version >= "2.7") and extra == "all"
Requires-Dist: pynmea2>=1.13.0; (python_version < "4.0" and python_version >= "3.12") and extra == "all"
Requires-Dist: pynmea2>=1.5.3; (python_version < "3.12" and python_version >= "3.6") and extra == "all"
Requires-Dist: tornado>=6.2; extra == "all"
Requires-Dist: psutil>=6.1.0; (python_version < "4.0" and python_version >= "3.13") and extra == "all"
Requires-Dist: psutil>=5.9.6; (python_version < "3.13" and python_version >= "3.12") and extra == "all"
Requires-Dist: psutil>=5.9.4; (python_version < "3.12" and python_version >= "3.11") and extra == "all"
Requires-Dist: psutil>=5.9.0; (python_version < "3.11" and python_version >= "3.10") and extra == "all"
Requires-Dist: psutil>=5.9.0; (python_version < "3.10" and python_version >= "3.9") and extra == "all"
Requires-Dist: matplotlib>=3.9.2; (python_version < "4.0" and python_version >= "3.13") and extra == "all"
Requires-Dist: matplotlib>=3.8.4; (python_version < "3.13" and python_version >= "3.12") and extra == "all"
Requires-Dist: matplotlib>=3.5.0; (python_version < "3.12" and python_version >= "3.11") and extra == "all"
Requires-Dist: matplotlib>=3.3.3; (python_version < "3.10" and python_version >= "3.9") and extra == "all"
Requires-Dist: matplotlib>=1.5.3; (python_version < "3.7" and python_version >= "3.6") and extra == "all"
Requires-Dist: numpy>=2.1.0; (python_version < "4.0" and python_version >= "3.13") and extra == "all"
Requires-Dist: numpy>=1.26.0; (python_version < "3.13" and python_version >= "3.12") and extra == "all"
Requires-Dist: numpy>=1.24.0; (python_version < "3.12" and python_version >= "3.11") and extra == "all"
Requires-Dist: numpy>=1.21.6; (python_version < "3.11" and python_version >= "3.10") and extra == "all"
Requires-Dist: numpy>=1.19.3; (python_version < "3.10" and python_version >= "3.9") and extra == "all"
Requires-Dist: scikit-image>=0.25.1; (python_version < "4.0" and python_version >= "3.13") and extra == "all"
Requires-Dist: scikit-image>=0.22.0; (python_version < "3.13" and python_version >= "3.12") and extra == "all"
Requires-Dist: scikit-image>=0.20.0; (python_version < "3.12" and python_version >= "3.11") and extra == "all"
Requires-Dist: scikit-image>=0.19.0; (python_version < "3.11" and python_version >= "3.10") and extra == "all"
Requires-Dist: scikit-image>=0.18.0; (python_version < "3.10" and python_version >= "3.9") and extra == "all"
Requires-Dist: scikit-learn>=1.5.2; (python_version < "4.0" and python_version >= "3.13") and extra == "all"
Requires-Dist: scikit-learn>=1.3.1; (python_version < "3.13" and python_version >= "3.12") and extra == "all"
Requires-Dist: scikit-learn>=1.1.3; (python_version < "3.12" and python_version >= "3.11") and extra == "all"
Requires-Dist: scikit-learn>=1.1.0; (python_version < "3.11" and python_version >= "3.10") and extra == "all"
Requires-Dist: scikit-learn>=1.0.2; (python_version < "3.10" and python_version >= "3.9") and extra == "all"
Requires-Dist: scipy>=1.14.1; (python_version < "4.0" and python_version >= "3.13") and extra == "all"
Requires-Dist: scipy>=1.11.2; (python_version < "3.13" and python_version >= "3.12") and extra == "all"
Requires-Dist: scipy>=1.9.2; (python_version < "3.12" and python_version >= "3.11") and extra == "all"
Requires-Dist: scipy>=1.8.0; (python_version < "3.11" and python_version >= "3.10") and extra == "all"
Requires-Dist: scipy>=1.8.0; (python_version < "3.10" and python_version >= "3.9") and extra == "all"
Requires-Dist: shapely>=2.0.6; (python_version < "4.0" and python_version >= "3.13") and extra == "all"
Requires-Dist: shapely>=2.0.2; (python_version < "3.13" and python_version >= "3.12") and extra == "all"
Requires-Dist: shapely>=2.0.1; (python_version < "3.12" and python_version >= "3.11") and extra == "all"
Requires-Dist: shapely>=1.8.2; (python_version < "3.11" and python_version >= "3.10") and extra == "all"
Requires-Dist: shapely>=1.7.1; (python_version < "3.10" and python_version >= "3.9") and extra == "all"
Requires-Dist: networkx>=3.0.0; (python_version < "4.0" and python_version >= "3.13") and extra == "all"
Requires-Dist: networkx>=2.8; (python_version < "3.13" and python_version >= "3.11") and extra == "all"
Requires-Dist: networkx>=2.7; (python_version < "3.11" and python_version >= "3.8") and extra == "all"
Requires-Dist: pandas>=2.2.3; (python_version < "4.0" and python_version >= "3.13") and extra == "all"
Requires-Dist: pandas>=2.1.1; (python_version < "3.13" and python_version >= "3.12") and extra == "all"
Requires-Dist: pandas>=1.5.0; (python_version < "3.12" and python_version >= "3.11") and extra == "all"
Requires-Dist: pandas>=1.3.5; (python_version < "3.11" and python_version >= "3.10") and extra == "all"
Requires-Dist: pandas>=1.4.0; (python_version < "3.10" and python_version >= "3.9") and extra == "all"
Requires-Dist: Pillow>=11.3.0; (python_version < "4.0" and python_version >= "3.13") and extra == "all"
Requires-Dist: Pillow>=10.0.0; (python_version < "3.13" and python_version >= "3.12") and extra == "all"
Requires-Dist: Pillow>=9.4.0; (python_version < "3.12" and python_version >= "3.11") and extra == "all"
Requires-Dist: Pillow>=9.1.0; (python_version < "3.11" and python_version >= "3.10") and extra == "all"
Requires-Dist: Pillow>=8.3.2; (python_version < "3.10" and python_version >= "3.9") and extra == "all"
Requires-Dist: cachetools>=5.0.0; (python_version < "4.0" and python_version >= "3.11") and extra == "all"
Requires-Dist: cachetools>=5.0.0; (python_version < "3.11" and python_version >= "3.10") and extra == "all"
Requires-Dist: cachetools>=4.2.0; (python_version < "3.10" and python_version >= "3.9") and extra == "all"
Requires-Dist: pyparsing>=3.0.7; extra == "all"
Requires-Dist: requests>=2.27.1; extra == "all"
Requires-Dist: safer>=4.4.1; extra == "all"
Requires-Dist: xdoctest>=1.1.5; extra == "all"
Requires-Dist: pytest>=8.1.1; (python_version < "4.0" and python_version >= "3.13") and extra == "all"
Requires-Dist: pytest>=8.1.1; (python_version < "3.13" and python_version >= "3.12") and extra == "all"
Requires-Dist: pytest>=8.1.1; (python_version < "3.12" and python_version >= "3.11") and extra == "all"
Requires-Dist: pytest>=6.2.5; (python_version < "3.11" and python_version >= "3.10") and extra == "all"
Requires-Dist: pytest>=6.2.5; (python_version < "3.10" and python_version >= "3.8") and extra == "all"
Requires-Dist: pytest-cov>=3.0.0; extra == "all"
Requires-Dist: coverage>=7.3.0; (python_version < "4.0" and python_version >= "3.12") and extra == "all"
Requires-Dist: coverage>=6.1.1; (python_version < "3.12" and python_version >= "3.10") and extra == "all"
Requires-Dist: coverage>=5.3.1; (python_version < "3.10" and python_version >= "3.9") and extra == "all"
Requires-Dist: coverage>=6.1.1; (python_version < "3.9" and python_version >= "3.8") and extra == "all"
Requires-Dist: timerit>=1.0.1; extra == "all"
Requires-Dist: kwimage>=0.9.23; extra == "all"
Requires-Dist: ansi2html>=1.7.0; (python_version < "4.0" and python_version >= "3.11") and extra == "all"
Requires-Dist: ansi2html>=1.7.0; (python_version < "3.11" and python_version >= "3.10") and extra == "all"
Requires-Dist: ansi2html>=1.6.0; (python_version < "3.10" and python_version >= "3.9") and extra == "all"
Requires-Dist: autopep8>=2.0.1; extra == "all"
Requires-Dist: pyfiglet>=0.7.2; extra == "all"
Requires-Dist: flask-cors>=3.0.10; extra == "all"
Requires-Dist: pydot>=1.3.0; extra == "all"
Requires-Dist: pydot-ng>=2.0.0; extra == "all"
Requires-Dist: jupyter>=1.0.0; extra == "all"
Provides-Extra: headless
Requires-Dist: opencv-python-headless>=4.10.0.84; (python_version < "4.0" and python_version >= "3.13") and extra == "headless"
Requires-Dist: opencv-python-headless>=4.5.5.64; (python_version < "3.13" and python_version >= "3.11") and extra == "headless"
Requires-Dist: opencv-python-headless>=4.5.4.58; (python_version < "3.11" and python_version >= "3.10") and extra == "headless"
Requires-Dist: opencv-python-headless>=3.4.15.55; (python_version < "3.10" and python_version >= "3.9") and extra == "headless"
Provides-Extra: graphics
Requires-Dist: opencv-python>=4.10.0.84; (python_version < "4.0" and python_version >= "3.13") and extra == "graphics"
Requires-Dist: opencv-python>=4.5.5.64; (python_version < "3.13" and python_version >= "3.11") and extra == "graphics"
Requires-Dist: opencv-python>=4.5.4.58; (python_version < "3.11" and python_version >= "3.10") and extra == "graphics"
Requires-Dist: opencv-python>=3.4.15.55; (python_version < "3.10" and python_version >= "3.9") and extra == "graphics"
Provides-Extra: docs
Requires-Dist: sphinx>=5.0.1; extra == "docs"
Requires-Dist: sphinx-autobuild>=2021.3.14; extra == "docs"
Requires-Dist: sphinx_rtd_theme>=1.0.0; extra == "docs"
Requires-Dist: sphinxcontrib-napoleon>=0.7; extra == "docs"
Requires-Dist: sphinx-autoapi>=1.8.4; extra == "docs"
Requires-Dist: Pygments>=2.9.0; extra == "docs"
Requires-Dist: myst_parser>=0.18.0; extra == "docs"
Requires-Dist: sphinx-reredirects>=0.0.1; extra == "docs"
Provides-Extra: optional
Requires-Dist: ansi2html>=1.7.0; (python_version < "4.0" and python_version >= "3.11") and extra == "optional"
Requires-Dist: ansi2html>=1.7.0; (python_version < "3.11" and python_version >= "3.10") and extra == "optional"
Requires-Dist: ansi2html>=1.6.0; (python_version < "3.10" and python_version >= "3.9") and extra == "optional"
Requires-Dist: autopep8>=2.0.1; extra == "optional"
Requires-Dist: pyfiglet>=0.7.2; extra == "optional"
Requires-Dist: flask-cors>=3.0.10; extra == "optional"
Requires-Dist: pydot>=1.3.0; extra == "optional"
Requires-Dist: pydot-ng>=2.0.0; extra == "optional"
Requires-Dist: jupyter>=1.0.0; extra == "optional"
Provides-Extra: problematic
Requires-Dist: pygraphviz; extra == "problematic"
Provides-Extra: runtime
Requires-Dist: utool>=2.2.0; extra == "runtime"
Requires-Dist: vtool_ibeis>=2.3.0; extra == "runtime"
Requires-Dist: dtool_ibeis>=1.1.2; extra == "runtime"
Requires-Dist: plottool_ibeis>=2.3.0; extra == "runtime"
Requires-Dist: guitool_ibeis>=2.2.0; extra == "runtime"
Requires-Dist: futures_actors>=0.0.5; extra == "runtime"
Requires-Dist: pyflann_ibeis>=2.4.1; extra == "runtime"
Requires-Dist: vtool_ibeis_ext>=0.1.2; extra == "runtime"
Requires-Dist: pyhesaff>=2.1.3; extra == "runtime"
Requires-Dist: flask>=2.1.3; extra == "runtime"
Requires-Dist: Werkzeug>=2.2.2; extra == "runtime"
Requires-Dist: pygments>=2.11.2; extra == "runtime"
Requires-Dist: packaging>=21.3; python_version >= "3.6" and extra == "runtime"
Requires-Dist: boto>=2.49.0; extra == "runtime"
Requires-Dist: colorama>=0.3.2; extra == "runtime"
Requires-Dist: IPython>=7.16.2; extra == "runtime"
Requires-Dist: parse>=1.19.0; extra == "runtime"
Requires-Dist: pyasn1>=0.4.8; extra == "runtime"
Requires-Dist: pyzmq>=26.0.0; (python_version < "4.0" and python_version >= "3.13") and extra == "runtime"
Requires-Dist: pyzmq>=26.0.0; (python_version < "3.13" and python_version >= "3.12") and extra == "runtime"
Requires-Dist: pyzmq>=25.0.0; python_version < "3.12" and extra == "runtime"
Requires-Dist: setuptools>=34.1.0; extra == "runtime"
Requires-Dist: simplejson>=3.6.5; extra == "runtime"
Requires-Dist: six>=1.16.0; extra == "runtime"
Requires-Dist: lockfile>=0.10.2; extra == "runtime"
Requires-Dist: statsmodels>=0.14.3; (python_version < "4.0" and python_version >= "3.13") and extra == "runtime"
Requires-Dist: statsmodels>=0.14.0; (python_version < "3.13" and python_version >= "3.12") and extra == "runtime"
Requires-Dist: statsmodels>=0.13.3; (python_version < "3.12" and python_version >= "3.11") and extra == "runtime"
Requires-Dist: statsmodels>=0.13.1; (python_version < "3.11" and python_version >= "3.10") and extra == "runtime"
Requires-Dist: statsmodels>=0.13.1; (python_version < "3.10" and python_version >= "3.9") and extra == "runtime"
Requires-Dist: ubelt>=1.3.4; extra == "runtime"
Requires-Dist: pyqt5>=5.15.10; (python_version < "4.0" and python_version >= "3.12") and extra == "runtime"
Requires-Dist: pyqt5>=5.15.5; (python_version < "3.12" and python_version >= "2.7") and extra == "runtime"
Requires-Dist: pynmea2>=1.13.0; (python_version < "4.0" and python_version >= "3.12") and extra == "runtime"
Requires-Dist: pynmea2>=1.5.3; (python_version < "3.12" and python_version >= "3.6") and extra == "runtime"
Requires-Dist: tornado>=6.2; extra == "runtime"
Requires-Dist: psutil>=6.1.0; (python_version < "4.0" and python_version >= "3.13") and extra == "runtime"
Requires-Dist: psutil>=5.9.6; (python_version < "3.13" and python_version >= "3.12") and extra == "runtime"
Requires-Dist: psutil>=5.9.4; (python_version < "3.12" and python_version >= "3.11") and extra == "runtime"
Requires-Dist: psutil>=5.9.0; (python_version < "3.11" and python_version >= "3.10") and extra == "runtime"
Requires-Dist: psutil>=5.9.0; (python_version < "3.10" and python_version >= "3.9") and extra == "runtime"
Requires-Dist: matplotlib>=3.9.2; (python_version < "4.0" and python_version >= "3.13") and extra == "runtime"
Requires-Dist: matplotlib>=3.8.4; (python_version < "3.13" and python_version >= "3.12") and extra == "runtime"
Requires-Dist: matplotlib>=3.5.0; (python_version < "3.12" and python_version >= "3.11") and extra == "runtime"
Requires-Dist: matplotlib>=3.3.3; (python_version < "3.10" and python_version >= "3.9") and extra == "runtime"
Requires-Dist: matplotlib>=1.5.3; (python_version < "3.7" and python_version >= "3.6") and extra == "runtime"
Requires-Dist: numpy>=2.1.0; (python_version < "4.0" and python_version >= "3.13") and extra == "runtime"
Requires-Dist: numpy>=1.26.0; (python_version < "3.13" and python_version >= "3.12") and extra == "runtime"
Requires-Dist: numpy>=1.24.0; (python_version < "3.12" and python_version >= "3.11") and extra == "runtime"
Requires-Dist: numpy>=1.21.6; (python_version < "3.11" and python_version >= "3.10") and extra == "runtime"
Requires-Dist: numpy>=1.19.3; (python_version < "3.10" and python_version >= "3.9") and extra == "runtime"
Requires-Dist: scikit-image>=0.25.1; (python_version < "4.0" and python_version >= "3.13") and extra == "runtime"
Requires-Dist: scikit-image>=0.22.0; (python_version < "3.13" and python_version >= "3.12") and extra == "runtime"
Requires-Dist: scikit-image>=0.20.0; (python_version < "3.12" and python_version >= "3.11") and extra == "runtime"
Requires-Dist: scikit-image>=0.19.0; (python_version < "3.11" and python_version >= "3.10") and extra == "runtime"
Requires-Dist: scikit-image>=0.18.0; (python_version < "3.10" and python_version >= "3.9") and extra == "runtime"
Requires-Dist: scikit-learn>=1.5.2; (python_version < "4.0" and python_version >= "3.13") and extra == "runtime"
Requires-Dist: scikit-learn>=1.3.1; (python_version < "3.13" and python_version >= "3.12") and extra == "runtime"
Requires-Dist: scikit-learn>=1.1.3; (python_version < "3.12" and python_version >= "3.11") and extra == "runtime"
Requires-Dist: scikit-learn>=1.1.0; (python_version < "3.11" and python_version >= "3.10") and extra == "runtime"
Requires-Dist: scikit-learn>=1.0.2; (python_version < "3.10" and python_version >= "3.9") and extra == "runtime"
Requires-Dist: scipy>=1.14.1; (python_version < "4.0" and python_version >= "3.13") and extra == "runtime"
Requires-Dist: scipy>=1.11.2; (python_version < "3.13" and python_version >= "3.12") and extra == "runtime"
Requires-Dist: scipy>=1.9.2; (python_version < "3.12" and python_version >= "3.11") and extra == "runtime"
Requires-Dist: scipy>=1.8.0; (python_version < "3.11" and python_version >= "3.10") and extra == "runtime"
Requires-Dist: scipy>=1.8.0; (python_version < "3.10" and python_version >= "3.9") and extra == "runtime"
Requires-Dist: shapely>=2.0.6; (python_version < "4.0" and python_version >= "3.13") and extra == "runtime"
Requires-Dist: shapely>=2.0.2; (python_version < "3.13" and python_version >= "3.12") and extra == "runtime"
Requires-Dist: shapely>=2.0.1; (python_version < "3.12" and python_version >= "3.11") and extra == "runtime"
Requires-Dist: shapely>=1.8.2; (python_version < "3.11" and python_version >= "3.10") and extra == "runtime"
Requires-Dist: shapely>=1.7.1; (python_version < "3.10" and python_version >= "3.9") and extra == "runtime"
Requires-Dist: networkx>=3.0.0; (python_version < "4.0" and python_version >= "3.13") and extra == "runtime"
Requires-Dist: networkx>=2.8; (python_version < "3.13" and python_version >= "3.11") and extra == "runtime"
Requires-Dist: networkx>=2.7; (python_version < "3.11" and python_version >= "3.8") and extra == "runtime"
Requires-Dist: pandas>=2.2.3; (python_version < "4.0" and python_version >= "3.13") and extra == "runtime"
Requires-Dist: pandas>=2.1.1; (python_version < "3.13" and python_version >= "3.12") and extra == "runtime"
Requires-Dist: pandas>=1.5.0; (python_version < "3.12" and python_version >= "3.11") and extra == "runtime"
Requires-Dist: pandas>=1.3.5; (python_version < "3.11" and python_version >= "3.10") and extra == "runtime"
Requires-Dist: pandas>=1.4.0; (python_version < "3.10" and python_version >= "3.9") and extra == "runtime"
Requires-Dist: Pillow>=11.3.0; (python_version < "4.0" and python_version >= "3.13") and extra == "runtime"
Requires-Dist: Pillow>=10.0.0; (python_version < "3.13" and python_version >= "3.12") and extra == "runtime"
Requires-Dist: Pillow>=9.4.0; (python_version < "3.12" and python_version >= "3.11") and extra == "runtime"
Requires-Dist: Pillow>=9.1.0; (python_version < "3.11" and python_version >= "3.10") and extra == "runtime"
Requires-Dist: Pillow>=8.3.2; (python_version < "3.10" and python_version >= "3.9") and extra == "runtime"
Requires-Dist: cachetools>=5.0.0; (python_version < "4.0" and python_version >= "3.11") and extra == "runtime"
Requires-Dist: cachetools>=5.0.0; (python_version < "3.11" and python_version >= "3.10") and extra == "runtime"
Requires-Dist: cachetools>=4.2.0; (python_version < "3.10" and python_version >= "3.9") and extra == "runtime"
Requires-Dist: pyparsing>=3.0.7; extra == "runtime"
Requires-Dist: requests>=2.27.1; extra == "runtime"
Requires-Dist: safer>=4.4.1; extra == "runtime"
Provides-Extra: super-setup
Requires-Dist: gitpython>=3.1.25; (python_version < "4.0" and python_version >= "3.11") and extra == "super-setup"
Requires-Dist: gitpython>=3.1.25; (python_version < "3.11" and python_version >= "3.10") and extra == "super-setup"
Requires-Dist: gitpython>=3.1.10; (python_version < "3.10" and python_version >= "3.9") and extra == "super-setup"
Requires-Dist: click>=8.0.2; (python_version < "4.0" and python_version >= "3.11") and extra == "super-setup"
Requires-Dist: click>=8.0.2; (python_version < "3.11" and python_version >= "3.10") and extra == "super-setup"
Requires-Dist: click>=8.0.0; (python_version < "3.10" and python_version >= "3.9") and extra == "super-setup"
Requires-Dist: ubelt>=1.2.3; extra == "super-setup"
Provides-Extra: tests
Requires-Dist: xdoctest>=1.1.5; extra == "tests"
Requires-Dist: pytest>=8.1.1; (python_version < "4.0" and python_version >= "3.13") and extra == "tests"
Requires-Dist: pytest>=8.1.1; (python_version < "3.13" and python_version >= "3.12") and extra == "tests"
Requires-Dist: pytest>=8.1.1; (python_version < "3.12" and python_version >= "3.11") and extra == "tests"
Requires-Dist: pytest>=6.2.5; (python_version < "3.11" and python_version >= "3.10") and extra == "tests"
Requires-Dist: pytest>=6.2.5; (python_version < "3.10" and python_version >= "3.8") and extra == "tests"
Requires-Dist: pytest-cov>=3.0.0; extra == "tests"
Requires-Dist: coverage>=7.3.0; (python_version < "4.0" and python_version >= "3.12") and extra == "tests"
Requires-Dist: coverage>=6.1.1; (python_version < "3.12" and python_version >= "3.10") and extra == "tests"
Requires-Dist: coverage>=5.3.1; (python_version < "3.10" and python_version >= "3.9") and extra == "tests"
Requires-Dist: coverage>=6.1.1; (python_version < "3.9" and python_version >= "3.8") and extra == "tests"
Requires-Dist: timerit>=1.0.1; extra == "tests"
Requires-Dist: kwimage>=0.9.23; extra == "tests"
Provides-Extra: all-strict
Requires-Dist: utool==2.2.0; extra == "all-strict"
Requires-Dist: vtool_ibeis==2.3.0; extra == "all-strict"
Requires-Dist: dtool_ibeis==1.1.2; extra == "all-strict"
Requires-Dist: plottool_ibeis==2.3.0; extra == "all-strict"
Requires-Dist: guitool_ibeis==2.2.0; extra == "all-strict"
Requires-Dist: futures_actors==0.0.5; extra == "all-strict"
Requires-Dist: pyflann_ibeis==2.4.1; extra == "all-strict"
Requires-Dist: vtool_ibeis_ext==0.1.2; extra == "all-strict"
Requires-Dist: pyhesaff==2.1.3; extra == "all-strict"
Requires-Dist: flask==2.1.3; extra == "all-strict"
Requires-Dist: Werkzeug==2.2.2; extra == "all-strict"
Requires-Dist: pygments==2.11.2; extra == "all-strict"
Requires-Dist: packaging==21.3; python_version >= "3.6" and extra == "all-strict"
Requires-Dist: boto==2.49.0; extra == "all-strict"
Requires-Dist: colorama==0.3.2; extra == "all-strict"
Requires-Dist: IPython==7.16.2; extra == "all-strict"
Requires-Dist: parse==1.19.0; extra == "all-strict"
Requires-Dist: pyasn1==0.4.8; extra == "all-strict"
Requires-Dist: pyzmq==26.0.0; (python_version < "4.0" and python_version >= "3.13") and extra == "all-strict"
Requires-Dist: pyzmq==26.0.0; (python_version < "3.13" and python_version >= "3.12") and extra == "all-strict"
Requires-Dist: pyzmq==25.0.0; python_version < "3.12" and extra == "all-strict"
Requires-Dist: setuptools==34.1.0; extra == "all-strict"
Requires-Dist: simplejson==3.6.5; extra == "all-strict"
Requires-Dist: six==1.16.0; extra == "all-strict"
Requires-Dist: lockfile==0.10.2; extra == "all-strict"
Requires-Dist: statsmodels==0.14.3; (python_version < "4.0" and python_version >= "3.13") and extra == "all-strict"
Requires-Dist: statsmodels==0.14.0; (python_version < "3.13" and python_version >= "3.12") and extra == "all-strict"
Requires-Dist: statsmodels==0.13.3; (python_version < "3.12" and python_version >= "3.11") and extra == "all-strict"
Requires-Dist: statsmodels==0.13.1; (python_version < "3.11" and python_version >= "3.10") and extra == "all-strict"
Requires-Dist: statsmodels==0.13.1; (python_version < "3.10" and python_version >= "3.9") and extra == "all-strict"
Requires-Dist: ubelt==1.3.4; extra == "all-strict"
Requires-Dist: pyqt5==5.15.10; (python_version < "4.0" and python_version >= "3.12") and extra == "all-strict"
Requires-Dist: pyqt5==5.15.5; (python_version < "3.12" and python_version >= "2.7") and extra == "all-strict"
Requires-Dist: pynmea2==1.13.0; (python_version < "4.0" and python_version >= "3.12") and extra == "all-strict"
Requires-Dist: pynmea2==1.5.3; (python_version < "3.12" and python_version >= "3.6") and extra == "all-strict"
Requires-Dist: tornado==6.2; extra == "all-strict"
Requires-Dist: psutil==6.1.0; (python_version < "4.0" and python_version >= "3.13") and extra == "all-strict"
Requires-Dist: psutil==5.9.6; (python_version < "3.13" and python_version >= "3.12") and extra == "all-strict"
Requires-Dist: psutil==5.9.4; (python_version < "3.12" and python_version >= "3.11") and extra == "all-strict"
Requires-Dist: psutil==5.9.0; (python_version < "3.11" and python_version >= "3.10") and extra == "all-strict"
Requires-Dist: psutil==5.9.0; (python_version < "3.10" and python_version >= "3.9") and extra == "all-strict"
Requires-Dist: matplotlib==3.9.2; (python_version < "4.0" and python_version >= "3.13") and extra == "all-strict"
Requires-Dist: matplotlib==3.8.4; (python_version < "3.13" and python_version >= "3.12") and extra == "all-strict"
Requires-Dist: matplotlib==3.5.0; (python_version < "3.12" and python_version >= "3.11") and extra == "all-strict"
Requires-Dist: matplotlib==3.3.3; (python_version < "3.10" and python_version >= "3.9") and extra == "all-strict"
Requires-Dist: matplotlib==1.5.3; (python_version < "3.7" and python_version >= "3.6") and extra == "all-strict"
Requires-Dist: numpy==2.1.0; (python_version < "4.0" and python_version >= "3.13") and extra == "all-strict"
Requires-Dist: numpy==1.26.0; (python_version < "3.13" and python_version >= "3.12") and extra == "all-strict"
Requires-Dist: numpy==1.24.0; (python_version < "3.12" and python_version >= "3.11") and extra == "all-strict"
Requires-Dist: numpy==1.21.6; (python_version < "3.11" and python_version >= "3.10") and extra == "all-strict"
Requires-Dist: numpy==1.19.3; (python_version < "3.10" and python_version >= "3.9") and extra == "all-strict"
Requires-Dist: scikit-image==0.25.1; (python_version < "4.0" and python_version >= "3.13") and extra == "all-strict"
Requires-Dist: scikit-image==0.22.0; (python_version < "3.13" and python_version >= "3.12") and extra == "all-strict"
Requires-Dist: scikit-image==0.20.0; (python_version < "3.12" and python_version >= "3.11") and extra == "all-strict"
Requires-Dist: scikit-image==0.19.0; (python_version < "3.11" and python_version >= "3.10") and extra == "all-strict"
Requires-Dist: scikit-image==0.18.0; (python_version < "3.10" and python_version >= "3.9") and extra == "all-strict"
Requires-Dist: scikit-learn==1.5.2; (python_version < "4.0" and python_version >= "3.13") and extra == "all-strict"
Requires-Dist: scikit-learn==1.3.1; (python_version < "3.13" and python_version >= "3.12") and extra == "all-strict"
Requires-Dist: scikit-learn==1.1.3; (python_version < "3.12" and python_version >= "3.11") and extra == "all-strict"
Requires-Dist: scikit-learn==1.1.0; (python_version < "3.11" and python_version >= "3.10") and extra == "all-strict"
Requires-Dist: scikit-learn==1.0.2; (python_version < "3.10" and python_version >= "3.9") and extra == "all-strict"
Requires-Dist: scipy==1.14.1; (python_version < "4.0" and python_version >= "3.13") and extra == "all-strict"
Requires-Dist: scipy==1.11.2; (python_version < "3.13" and python_version >= "3.12") and extra == "all-strict"
Requires-Dist: scipy==1.9.2; (python_version < "3.12" and python_version >= "3.11") and extra == "all-strict"
Requires-Dist: scipy==1.8.0; (python_version < "3.11" and python_version >= "3.10") and extra == "all-strict"
Requires-Dist: scipy==1.8.0; (python_version < "3.10" and python_version >= "3.9") and extra == "all-strict"
Requires-Dist: shapely==2.0.6; (python_version < "4.0" and python_version >= "3.13") and extra == "all-strict"
Requires-Dist: shapely==2.0.2; (python_version < "3.13" and python_version >= "3.12") and extra == "all-strict"
Requires-Dist: shapely==2.0.1; (python_version < "3.12" and python_version >= "3.11") and extra == "all-strict"
Requires-Dist: shapely==1.8.2; (python_version < "3.11" and python_version >= "3.10") and extra == "all-strict"
Requires-Dist: shapely==1.7.1; (python_version < "3.10" and python_version >= "3.9") and extra == "all-strict"
Requires-Dist: networkx==3.0.0; (python_version < "4.0" and python_version >= "3.13") and extra == "all-strict"
Requires-Dist: networkx==2.8; (python_version < "3.13" and python_version >= "3.11") and extra == "all-strict"
Requires-Dist: networkx==2.7; (python_version < "3.11" and python_version >= "3.8") and extra == "all-strict"
Requires-Dist: pandas==2.2.3; (python_version < "4.0" and python_version >= "3.13") and extra == "all-strict"
Requires-Dist: pandas==2.1.1; (python_version < "3.13" and python_version >= "3.12") and extra == "all-strict"
Requires-Dist: pandas==1.5.0; (python_version < "3.12" and python_version >= "3.11") and extra == "all-strict"
Requires-Dist: pandas==1.3.5; (python_version < "3.11" and python_version >= "3.10") and extra == "all-strict"
Requires-Dist: pandas==1.4.0; (python_version < "3.10" and python_version >= "3.9") and extra == "all-strict"
Requires-Dist: Pillow==11.3.0; (python_version < "4.0" and python_version >= "3.13") and extra == "all-strict"
Requires-Dist: Pillow==10.0.0; (python_version < "3.13" and python_version >= "3.12") and extra == "all-strict"
Requires-Dist: Pillow==9.4.0; (python_version < "3.12" and python_version >= "3.11") and extra == "all-strict"
Requires-Dist: Pillow==9.1.0; (python_version < "3.11" and python_version >= "3.10") and extra == "all-strict"
Requires-Dist: Pillow==8.3.2; (python_version < "3.10" and python_version >= "3.9") and extra == "all-strict"
Requires-Dist: cachetools==5.0.0; (python_version < "4.0" and python_version >= "3.11") and extra == "all-strict"
Requires-Dist: cachetools==5.0.0; (python_version < "3.11" and python_version >= "3.10") and extra == "all-strict"
Requires-Dist: cachetools==4.2.0; (python_version < "3.10" and python_version >= "3.9") and extra == "all-strict"
Requires-Dist: pyparsing==3.0.7; extra == "all-strict"
Requires-Dist: requests==2.27.1; extra == "all-strict"
Requires-Dist: safer==4.4.1; extra == "all-strict"
Requires-Dist: xdoctest==1.1.5; extra == "all-strict"
Requires-Dist: pytest==8.1.1; (python_version < "4.0" and python_version >= "3.13") and extra == "all-strict"
Requires-Dist: pytest==8.1.1; (python_version < "3.13" and python_version >= "3.12") and extra == "all-strict"
Requires-Dist: pytest==8.1.1; (python_version < "3.12" and python_version >= "3.11") and extra == "all-strict"
Requires-Dist: pytest==6.2.5; (python_version < "3.11" and python_version >= "3.10") and extra == "all-strict"
Requires-Dist: pytest==6.2.5; (python_version < "3.10" and python_version >= "3.8") and extra == "all-strict"
Requires-Dist: pytest-cov==3.0.0; extra == "all-strict"
Requires-Dist: coverage==7.3.0; (python_version < "4.0" and python_version >= "3.12") and extra == "all-strict"
Requires-Dist: coverage==6.1.1; (python_version < "3.12" and python_version >= "3.10") and extra == "all-strict"
Requires-Dist: coverage==5.3.1; (python_version < "3.10" and python_version >= "3.9") and extra == "all-strict"
Requires-Dist: coverage==6.1.1; (python_version < "3.9" and python_version >= "3.8") and extra == "all-strict"
Requires-Dist: timerit==1.0.1; extra == "all-strict"
Requires-Dist: kwimage==0.9.23; extra == "all-strict"
Requires-Dist: ansi2html==1.7.0; (python_version < "4.0" and python_version >= "3.11") and extra == "all-strict"
Requires-Dist: ansi2html==1.7.0; (python_version < "3.11" and python_version >= "3.10") and extra == "all-strict"
Requires-Dist: ansi2html==1.6.0; (python_version < "3.10" and python_version >= "3.9") and extra == "all-strict"
Requires-Dist: autopep8==2.0.1; extra == "all-strict"
Requires-Dist: pyfiglet==0.7.2; extra == "all-strict"
Requires-Dist: flask-cors==3.0.10; extra == "all-strict"
Requires-Dist: pydot==1.3.0; extra == "all-strict"
Requires-Dist: pydot-ng==2.0.0; extra == "all-strict"
Requires-Dist: jupyter==1.0.0; extra == "all-strict"
Provides-Extra: headless-strict
Requires-Dist: opencv-python-headless==4.10.0.84; (python_version < "4.0" and python_version >= "3.13") and extra == "headless-strict"
Requires-Dist: opencv-python-headless==4.5.5.64; (python_version < "3.13" and python_version >= "3.11") and extra == "headless-strict"
Requires-Dist: opencv-python-headless==4.5.4.58; (python_version < "3.11" and python_version >= "3.10") and extra == "headless-strict"
Requires-Dist: opencv-python-headless==3.4.15.55; (python_version < "3.10" and python_version >= "3.9") and extra == "headless-strict"
Provides-Extra: graphics-strict
Requires-Dist: opencv-python==4.10.0.84; (python_version < "4.0" and python_version >= "3.13") and extra == "graphics-strict"
Requires-Dist: opencv-python==4.5.5.64; (python_version < "3.13" and python_version >= "3.11") and extra == "graphics-strict"
Requires-Dist: opencv-python==4.5.4.58; (python_version < "3.11" and python_version >= "3.10") and extra == "graphics-strict"
Requires-Dist: opencv-python==3.4.15.55; (python_version < "3.10" and python_version >= "3.9") and extra == "graphics-strict"
Provides-Extra: docs-strict
Requires-Dist: sphinx==5.0.1; extra == "docs-strict"
Requires-Dist: sphinx-autobuild==2021.3.14; extra == "docs-strict"
Requires-Dist: sphinx_rtd_theme==1.0.0; extra == "docs-strict"
Requires-Dist: sphinxcontrib-napoleon==0.7; extra == "docs-strict"
Requires-Dist: sphinx-autoapi==1.8.4; extra == "docs-strict"
Requires-Dist: Pygments==2.9.0; extra == "docs-strict"
Requires-Dist: myst_parser==0.18.0; extra == "docs-strict"
Requires-Dist: sphinx-reredirects==0.0.1; extra == "docs-strict"
Provides-Extra: optional-strict
Requires-Dist: ansi2html==1.7.0; (python_version < "4.0" and python_version >= "3.11") and extra == "optional-strict"
Requires-Dist: ansi2html==1.7.0; (python_version < "3.11" and python_version >= "3.10") and extra == "optional-strict"
Requires-Dist: ansi2html==1.6.0; (python_version < "3.10" and python_version >= "3.9") and extra == "optional-strict"
Requires-Dist: autopep8==2.0.1; extra == "optional-strict"
Requires-Dist: pyfiglet==0.7.2; extra == "optional-strict"
Requires-Dist: flask-cors==3.0.10; extra == "optional-strict"
Requires-Dist: pydot==1.3.0; extra == "optional-strict"
Requires-Dist: pydot-ng==2.0.0; extra == "optional-strict"
Requires-Dist: jupyter==1.0.0; extra == "optional-strict"
Provides-Extra: problematic-strict
Requires-Dist: pygraphviz; extra == "problematic-strict"
Provides-Extra: runtime-strict
Requires-Dist: utool==2.2.0; extra == "runtime-strict"
Requires-Dist: vtool_ibeis==2.3.0; extra == "runtime-strict"
Requires-Dist: dtool_ibeis==1.1.2; extra == "runtime-strict"
Requires-Dist: plottool_ibeis==2.3.0; extra == "runtime-strict"
Requires-Dist: guitool_ibeis==2.2.0; extra == "runtime-strict"
Requires-Dist: futures_actors==0.0.5; extra == "runtime-strict"
Requires-Dist: pyflann_ibeis==2.4.1; extra == "runtime-strict"
Requires-Dist: vtool_ibeis_ext==0.1.2; extra == "runtime-strict"
Requires-Dist: pyhesaff==2.1.3; extra == "runtime-strict"
Requires-Dist: flask==2.1.3; extra == "runtime-strict"
Requires-Dist: Werkzeug==2.2.2; extra == "runtime-strict"
Requires-Dist: pygments==2.11.2; extra == "runtime-strict"
Requires-Dist: packaging==21.3; python_version >= "3.6" and extra == "runtime-strict"
Requires-Dist: boto==2.49.0; extra == "runtime-strict"
Requires-Dist: colorama==0.3.2; extra == "runtime-strict"
Requires-Dist: IPython==7.16.2; extra == "runtime-strict"
Requires-Dist: parse==1.19.0; extra == "runtime-strict"
Requires-Dist: pyasn1==0.4.8; extra == "runtime-strict"
Requires-Dist: pyzmq==26.0.0; (python_version < "4.0" and python_version >= "3.13") and extra == "runtime-strict"
Requires-Dist: pyzmq==26.0.0; (python_version < "3.13" and python_version >= "3.12") and extra == "runtime-strict"
Requires-Dist: pyzmq==25.0.0; python_version < "3.12" and extra == "runtime-strict"
Requires-Dist: setuptools==34.1.0; extra == "runtime-strict"
Requires-Dist: simplejson==3.6.5; extra == "runtime-strict"
Requires-Dist: six==1.16.0; extra == "runtime-strict"
Requires-Dist: lockfile==0.10.2; extra == "runtime-strict"
Requires-Dist: statsmodels==0.14.3; (python_version < "4.0" and python_version >= "3.13") and extra == "runtime-strict"
Requires-Dist: statsmodels==0.14.0; (python_version < "3.13" and python_version >= "3.12") and extra == "runtime-strict"
Requires-Dist: statsmodels==0.13.3; (python_version < "3.12" and python_version >= "3.11") and extra == "runtime-strict"
Requires-Dist: statsmodels==0.13.1; (python_version < "3.11" and python_version >= "3.10") and extra == "runtime-strict"
Requires-Dist: statsmodels==0.13.1; (python_version < "3.10" and python_version >= "3.9") and extra == "runtime-strict"
Requires-Dist: ubelt==1.3.4; extra == "runtime-strict"
Requires-Dist: pyqt5==5.15.10; (python_version < "4.0" and python_version >= "3.12") and extra == "runtime-strict"
Requires-Dist: pyqt5==5.15.5; (python_version < "3.12" and python_version >= "2.7") and extra == "runtime-strict"
Requires-Dist: pynmea2==1.13.0; (python_version < "4.0" and python_version >= "3.12") and extra == "runtime-strict"
Requires-Dist: pynmea2==1.5.3; (python_version < "3.12" and python_version >= "3.6") and extra == "runtime-strict"
Requires-Dist: tornado==6.2; extra == "runtime-strict"
Requires-Dist: psutil==6.1.0; (python_version < "4.0" and python_version >= "3.13") and extra == "runtime-strict"
Requires-Dist: psutil==5.9.6; (python_version < "3.13" and python_version >= "3.12") and extra == "runtime-strict"
Requires-Dist: psutil==5.9.4; (python_version < "3.12" and python_version >= "3.11") and extra == "runtime-strict"
Requires-Dist: psutil==5.9.0; (python_version < "3.11" and python_version >= "3.10") and extra == "runtime-strict"
Requires-Dist: psutil==5.9.0; (python_version < "3.10" and python_version >= "3.9") and extra == "runtime-strict"
Requires-Dist: matplotlib==3.9.2; (python_version < "4.0" and python_version >= "3.13") and extra == "runtime-strict"
Requires-Dist: matplotlib==3.8.4; (python_version < "3.13" and python_version >= "3.12") and extra == "runtime-strict"
Requires-Dist: matplotlib==3.5.0; (python_version < "3.12" and python_version >= "3.11") and extra == "runtime-strict"
Requires-Dist: matplotlib==3.3.3; (python_version < "3.10" and python_version >= "3.9") and extra == "runtime-strict"
Requires-Dist: matplotlib==1.5.3; (python_version < "3.7" and python_version >= "3.6") and extra == "runtime-strict"
Requires-Dist: numpy==2.1.0; (python_version < "4.0" and python_version >= "3.13") and extra == "runtime-strict"
Requires-Dist: numpy==1.26.0; (python_version < "3.13" and python_version >= "3.12") and extra == "runtime-strict"
Requires-Dist: numpy==1.24.0; (python_version < "3.12" and python_version >= "3.11") and extra == "runtime-strict"
Requires-Dist: numpy==1.21.6; (python_version < "3.11" and python_version >= "3.10") and extra == "runtime-strict"
Requires-Dist: numpy==1.19.3; (python_version < "3.10" and python_version >= "3.9") and extra == "runtime-strict"
Requires-Dist: scikit-image==0.25.1; (python_version < "4.0" and python_version >= "3.13") and extra == "runtime-strict"
Requires-Dist: scikit-image==0.22.0; (python_version < "3.13" and python_version >= "3.12") and extra == "runtime-strict"
Requires-Dist: scikit-image==0.20.0; (python_version < "3.12" and python_version >= "3.11") and extra == "runtime-strict"
Requires-Dist: scikit-image==0.19.0; (python_version < "3.11" and python_version >= "3.10") and extra == "runtime-strict"
Requires-Dist: scikit-image==0.18.0; (python_version < "3.10" and python_version >= "3.9") and extra == "runtime-strict"
Requires-Dist: scikit-learn==1.5.2; (python_version < "4.0" and python_version >= "3.13") and extra == "runtime-strict"
Requires-Dist: scikit-learn==1.3.1; (python_version < "3.13" and python_version >= "3.12") and extra == "runtime-strict"
Requires-Dist: scikit-learn==1.1.3; (python_version < "3.12" and python_version >= "3.11") and extra == "runtime-strict"
Requires-Dist: scikit-learn==1.1.0; (python_version < "3.11" and python_version >= "3.10") and extra == "runtime-strict"
Requires-Dist: scikit-learn==1.0.2; (python_version < "3.10" and python_version >= "3.9") and extra == "runtime-strict"
Requires-Dist: scipy==1.14.1; (python_version < "4.0" and python_version >= "3.13") and extra == "runtime-strict"
Requires-Dist: scipy==1.11.2; (python_version < "3.13" and python_version >= "3.12") and extra == "runtime-strict"
Requires-Dist: scipy==1.9.2; (python_version < "3.12" and python_version >= "3.11") and extra == "runtime-strict"
Requires-Dist: scipy==1.8.0; (python_version < "3.11" and python_version >= "3.10") and extra == "runtime-strict"
Requires-Dist: scipy==1.8.0; (python_version < "3.10" and python_version >= "3.9") and extra == "runtime-strict"
Requires-Dist: shapely==2.0.6; (python_version < "4.0" and python_version >= "3.13") and extra == "runtime-strict"
Requires-Dist: shapely==2.0.2; (python_version < "3.13" and python_version >= "3.12") and extra == "runtime-strict"
Requires-Dist: shapely==2.0.1; (python_version < "3.12" and python_version >= "3.11") and extra == "runtime-strict"
Requires-Dist: shapely==1.8.2; (python_version < "3.11" and python_version >= "3.10") and extra == "runtime-strict"
Requires-Dist: shapely==1.7.1; (python_version < "3.10" and python_version >= "3.9") and extra == "runtime-strict"
Requires-Dist: networkx==3.0.0; (python_version < "4.0" and python_version >= "3.13") and extra == "runtime-strict"
Requires-Dist: networkx==2.8; (python_version < "3.13" and python_version >= "3.11") and extra == "runtime-strict"
Requires-Dist: networkx==2.7; (python_version < "3.11" and python_version >= "3.8") and extra == "runtime-strict"
Requires-Dist: pandas==2.2.3; (python_version < "4.0" and python_version >= "3.13") and extra == "runtime-strict"
Requires-Dist: pandas==2.1.1; (python_version < "3.13" and python_version >= "3.12") and extra == "runtime-strict"
Requires-Dist: pandas==1.5.0; (python_version < "3.12" and python_version >= "3.11") and extra == "runtime-strict"
Requires-Dist: pandas==1.3.5; (python_version < "3.11" and python_version >= "3.10") and extra == "runtime-strict"
Requires-Dist: pandas==1.4.0; (python_version < "3.10" and python_version >= "3.9") and extra == "runtime-strict"
Requires-Dist: Pillow==11.3.0; (python_version < "4.0" and python_version >= "3.13") and extra == "runtime-strict"
Requires-Dist: Pillow==10.0.0; (python_version < "3.13" and python_version >= "3.12") and extra == "runtime-strict"
Requires-Dist: Pillow==9.4.0; (python_version < "3.12" and python_version >= "3.11") and extra == "runtime-strict"
Requires-Dist: Pillow==9.1.0; (python_version < "3.11" and python_version >= "3.10") and extra == "runtime-strict"
Requires-Dist: Pillow==8.3.2; (python_version < "3.10" and python_version >= "3.9") and extra == "runtime-strict"
Requires-Dist: cachetools==5.0.0; (python_version < "4.0" and python_version >= "3.11") and extra == "runtime-strict"
Requires-Dist: cachetools==5.0.0; (python_version < "3.11" and python_version >= "3.10") and extra == "runtime-strict"
Requires-Dist: cachetools==4.2.0; (python_version < "3.10" and python_version >= "3.9") and extra == "runtime-strict"
Requires-Dist: pyparsing==3.0.7; extra == "runtime-strict"
Requires-Dist: requests==2.27.1; extra == "runtime-strict"
Requires-Dist: safer==4.4.1; extra == "runtime-strict"
Provides-Extra: super-setup-strict
Requires-Dist: gitpython==3.1.25; (python_version < "4.0" and python_version >= "3.11") and extra == "super-setup-strict"
Requires-Dist: gitpython==3.1.25; (python_version < "3.11" and python_version >= "3.10") and extra == "super-setup-strict"
Requires-Dist: gitpython==3.1.10; (python_version < "3.10" and python_version >= "3.9") and extra == "super-setup-strict"
Requires-Dist: click==8.0.2; (python_version < "4.0" and python_version >= "3.11") and extra == "super-setup-strict"
Requires-Dist: click==8.0.2; (python_version < "3.11" and python_version >= "3.10") and extra == "super-setup-strict"
Requires-Dist: click==8.0.0; (python_version < "3.10" and python_version >= "3.9") and extra == "super-setup-strict"
Requires-Dist: ubelt==1.2.3; extra == "super-setup-strict"
Provides-Extra: tests-strict
Requires-Dist: xdoctest==1.1.5; extra == "tests-strict"
Requires-Dist: pytest==8.1.1; (python_version < "4.0" and python_version >= "3.13") and extra == "tests-strict"
Requires-Dist: pytest==8.1.1; (python_version < "3.13" and python_version >= "3.12") and extra == "tests-strict"
Requires-Dist: pytest==8.1.1; (python_version < "3.12" and python_version >= "3.11") and extra == "tests-strict"
Requires-Dist: pytest==6.2.5; (python_version < "3.11" and python_version >= "3.10") and extra == "tests-strict"
Requires-Dist: pytest==6.2.5; (python_version < "3.10" and python_version >= "3.8") and extra == "tests-strict"
Requires-Dist: pytest-cov==3.0.0; extra == "tests-strict"
Requires-Dist: coverage==7.3.0; (python_version < "4.0" and python_version >= "3.12") and extra == "tests-strict"
Requires-Dist: coverage==6.1.1; (python_version < "3.12" and python_version >= "3.10") and extra == "tests-strict"
Requires-Dist: coverage==5.3.1; (python_version < "3.10" and python_version >= "3.9") and extra == "tests-strict"
Requires-Dist: coverage==6.1.1; (python_version < "3.9" and python_version >= "3.8") and extra == "tests-strict"
Requires-Dist: timerit==1.0.1; extra == "tests-strict"
Requires-Dist: kwimage==0.9.23; extra == "tests-strict"
Dynamic: author
Dynamic: author-email
Dynamic: classifier
Dynamic: description
Dynamic: description-content-type
Dynamic: home-page
Dynamic: license
Dynamic: license-file
Dynamic: provides-extra
Dynamic: requires-dist
Dynamic: requires-python
Dynamic: summary
